gredos2x/__init__.py
gredos2x/gredos2gpkg.py
gredos2x/gredos2pgsql.py
gredos2x/gredos_gpkg2dataframes.py
gredos2x-1.0.5.dist-info/LICENSE.txt
gredos2x-1.0.5.dist-info/METADATA
gredos2x-1.0.5.dist-info/WHEEL
gredos2x-1.0.5.dist-info/top_level.txt
gredos2x-1.0.5.dist-info/RECORD
